{
	"$schema": "http://schema.management.azure.com/schemas/2015-01-01/deploymentTemplate.json#",
	"contentVersion": "1.0.0.0",
	"parameters": {
		"factoryName": {
			"type": "string",
			"metadata": "Data Factory Name",
			"defaultValue": "p21d19901010001"
		},
		"TimeDimension_Archive_Destination_properties_typeProperties_fileName": {
			"type": "string",
			"defaultValue": "@concat ('TimeDimension_' , formatDateTime(utcnow(), 'yyyy'), formatDateTime(utcnow(), 'MM'), formatDateTime(utcnow(), 'dd'))"
		},
		"TimeDimension_Archive_Destination_properties_typeProperties_folderPath": {
			"type": "string",
			"defaultValue": "LandingArchive/CEOCFO/Dimentions/Time"
		},
		"TimeDimension_Source_properties_typeProperties_fileName": {
			"type": "string",
			"defaultValue": "TimeDimension.csv"
		},
		"TimeDimension_Source_properties_typeProperties_folderPath": {
			"type": "string",
			"defaultValue": "CEOCFO/Dimentions/Time"
		},
		"User_Arch_Dest_properties_typeProperties_fileName": {
			"type": "string",
			"defaultValue": "@concat ('User_Initial_' , formatDateTime(utcnow(), 'yyyy'), formatDateTime(utcnow(), 'MM'), formatDateTime(utcnow(), 'dd'),'.orc')"
		},
		"User_Arch_Dest_properties_typeProperties_folderPath": {
			"type": "string",
			"defaultValue": "LandingArchive/CEOCFO/Sales/User"
		},
		"User_Arch_Dest_Incr_properties_typeProperties_fileName": {
			"type": "string",
			"defaultValue": "@concat ('User_' , formatDateTime(utcnow(), 'yyyy'), formatDateTime(utcnow(), 'MM'), formatDateTime(utcnow(), 'dd'),'.orc')"
		},
		"User_Arch_Dest_Incr_properties_typeProperties_folderPath": {
			"type": "string",
			"defaultValue": "LandingArchive/CEOCFO/Sales/User"
		},
		"V_HR_Maclean_EXM_Location_Archive_Destination_properties_typeProperties_fileName": {
			"type": "string",
			"defaultValue": "@concat ('EXM_Location_' , formatDateTime(utcnow(), 'yyyy'), formatDateTime(utcnow(), 'MM'), formatDateTime(utcnow(), 'dd'))"
		},
		"V_HR_Maclean_EXM_Location_Archive_Destination_properties_typeProperties_folderPath": {
			"type": "string",
			"defaultValue": "LandingArchive/CEOCFO/HR"
		},
		"V_HR_Maclean_EXM_Location_Directory_Archive_Destination_properties_typeProperties_fileName": {
			"type": "string",
			"defaultValue": "@concat ('HR_Maclean_EXM_Location_Directory_' , formatDateTime(utcnow(), 'yyyy'), formatDateTime(utcnow(), 'MM'), formatDateTime(utcnow(), 'dd'))"
		},
		"V_HR_Maclean_EXM_Location_Directory_Archive_Destination_properties_typeProperties_folderPath": {
			"type": "string",
			"defaultValue": "LandingArchive/HR"
		},
		"test_properties_typeProperties_fileName": {
			"type": "string",
			"defaultValue": "TimeDimens.csv"
		},
		"test_properties_typeProperties_folderPath": {
			"type": "string",
			"defaultValue": "Time"
		}
	},
	"variables": {
		"factoryId": "[concat('Microsoft.DataFactory/factories/', parameters('factoryName'))]"
	},
	"resources": [
		{
			"name": "[concat(parameters('factoryName'), '/TimeDimension_Archive_Destination')]",
			"type": "Microsoft.DataFactory/factories/datasets",
			"apiVersion": "2018-06-01",
			"properties": {
				"linkedServiceName": {
					"referenceName": "AzureDataLakeStore",
					"type": "LinkedServiceReference"
				},
				"annotations": [],
				"type": "AzureDataLakeStoreFile",
				"typeProperties": {
					"format": {
						"type": "TextFormat",
						"columnDelimiter": ",",
						"rowDelimiter": "",
						"quoteChar": "\"",
						"nullValue": "",
						"treatEmptyAsNull": true,
						"skipLineCount": 0,
						"firstRowAsHeader": true
					},
					"compression": {
						"type": "GZip",
						"level": "Optimal"
					},
					"fileName": {
						"value": "[parameters('TimeDimension_Archive_Destination_properties_typeProperties_fileName')]",
						"type": "Expression"
					},
					"folderPath": "[parameters('TimeDimension_Archive_Destination_properties_typeProperties_folderPath')]"
				}
			},
			"dependsOn": []
		},
		{
			"name": "[concat(parameters('factoryName'), '/TimeDimension_Destination')]",
			"type": "Microsoft.DataFactory/factories/datasets",
			"apiVersion": "2018-06-01",
			"properties": {
				"linkedServiceName": {
					"referenceName": "AzureSqlDatabase_finastra",
					"type": "LinkedServiceReference"
				},
				"annotations": [],
				"type": "AzureSqlTable",
				"structure": [
					{
						"name": "FISCAL_PERIOD_SKEY",
						"type": "String"
					},
					{
						"name": "FISCAL_PERIOD_CREAT_DT",
						"type": "String"
					},
					{
						"name": "FISCAL_PERIOD_LAST_UPD_DT",
						"type": "String"
					},
					{
						"name": "FISC_PERIOD_BKEY",
						"type": "String"
					},
					{
						"name": "FISC_PERIOD_CAPTION",
						"type": "String"
					},
					{
						"name": "FISC_PERIOD_CODE",
						"type": "String"
					},
					{
						"name": "FISC_PERIOD_NAME",
						"type": "String"
					},
					{
						"name": "FISC_PERIOD_SERIES",
						"type": "String"
					},
					{
						"name": "FISC_PERIOD_BEG_DT",
						"type": "String"
					},
					{
						"name": "FISC_PERIOD_END_DT",
						"type": "String"
					},
					{
						"name": "FISC_QTR_BKEY",
						"type": "String"
					},
					{
						"name": "FISC_QTR_CAPTION",
						"type": "String"
					},
					{
						"name": "FISC_QTR_CODE",
						"type": "String"
					},
					{
						"name": "FISC_QTR_NAME",
						"type": "String"
					},
					{
						"name": "FISC_QTR_SERIES",
						"type": "String"
					},
					{
						"name": "FISC_QTR_BEG_DT",
						"type": "String"
					},
					{
						"name": "FISC_QTR_END_DT",
						"type": "String"
					},
					{
						"name": "FISC_HALF_YEAR_BKEY",
						"type": "String"
					},
					{
						"name": "FISC_HALF_YEAR_CAPTION",
						"type": "String"
					},
					{
						"name": "FISC_HALF_YEAR_CODE",
						"type": "String"
					},
					{
						"name": "FISC_HALF_YEAR_NAME",
						"type": "String"
					},
					{
						"name": "FISC_HALF_YEAR_SERIES",
						"type": "String"
					},
					{
						"name": "FISC_HALF_YEAR_BEG_DT",
						"type": "String"
					},
					{
						"name": "FISC_HALF_YEAR_END_DT",
						"type": "String"
					},
					{
						"name": "FISC_YEAR_BKEY",
						"type": "String"
					},
					{
						"name": "FISC_YEAR_CAPTION",
						"type": "String"
					},
					{
						"name": "FISC_YEAR_CODE",
						"type": "String"
					},
					{
						"name": "FISC_YEAR_SERIES",
						"type": "String"
					},
					{
						"name": "FISC_YEAR_BEG_DT",
						"type": "String"
					},
					{
						"name": "FISC_YEAR_END_DT",
						"type": "String"
					},
					{
						"name": "FISC_YEAR_NAME",
						"type": "String"
					},
					{
						"name": "CAL_MONTH_BKEY",
						"type": "String"
					},
					{
						"name": "CAL_MONTH_CAPTION",
						"type": "String"
					},
					{
						"name": "CAL_MONTH_CODE",
						"type": "String"
					},
					{
						"name": "CAL_MONTH_NAME",
						"type": "String"
					},
					{
						"name": "CAL_MONTH_SERIES",
						"type": "String"
					},
					{
						"name": "CAL_MONTH_BEG_DT",
						"type": "String"
					},
					{
						"name": "CAL_MONTH_END_DT",
						"type": "String"
					},
					{
						"name": "CAL_QTR_BKEY",
						"type": "String"
					},
					{
						"name": "CAL_QTR_CAPTION",
						"type": "String"
					},
					{
						"name": "CAL_QTR_CODE",
						"type": "String"
					},
					{
						"name": "CAL_QTR_NAME",
						"type": "String"
					},
					{
						"name": "CAL_QTR_SERIES",
						"type": "String"
					},
					{
						"name": "CAL_QTR_BEG_DT",
						"type": "String"
					},
					{
						"name": "CAL_QTR_END_DT",
						"type": "String"
					},
					{
						"name": "CAL_HALF_YEAR_BKEY",
						"type": "String"
					},
					{
						"name": "CAL_HALF_YEAR_CAPTION",
						"type": "String"
					},
					{
						"name": "CAL_HALF_YEAR_CODE",
						"type": "String"
					},
					{
						"name": "CAL_HALF_YEAR_NAME",
						"type": "String"
					},
					{
						"name": "CAL_HALF_YEAR_SERIES",
						"type": "String"
					},
					{
						"name": "CAL_HALF_YEAR_BEG_DT",
						"type": "String"
					},
					{
						"name": "CAL_HALF_YEAR_END_DT",
						"type": "String"
					},
					{
						"name": "CAL_YEAR_BKEY",
						"type": "String"
					},
					{
						"name": "CAL_YEAR_CAPTION",
						"type": "String"
					},
					{
						"name": "CAL_YEAR_CODE",
						"type": "String"
					},
					{
						"name": "CAL_YEAR_SERIES",
						"type": "String"
					},
					{
						"name": "CAL_YEAR_BEG_DT",
						"type": "String"
					},
					{
						"name": "CAL_YEAR_END_DT",
						"type": "String"
					},
					{
						"name": "CAL_YEAR_NAME",
						"type": "String"
					},
					{
						"name": "SOURCE_SYSTEM",
						"type": "String"
					}
				],
				"typeProperties": {
					"tableName": "[[STG].[TimeDimension]"
				}
			},
			"dependsOn": []
		},
		{
			"name": "[concat(parameters('factoryName'), '/TimeDimension_Source')]",
			"type": "Microsoft.DataFactory/factories/datasets",
			"apiVersion": "2018-06-01",
			"properties": {
				"linkedServiceName": {
					"referenceName": "FileShare",
					"type": "LinkedServiceReference"
				},
				"annotations": [],
				"type": "FileShare",
				"structure": [
					{
						"name": "FISCAL_PERIOD_SKEY",
						"type": "String"
					},
					{
						"name": "FISCAL_PERIOD_CREAT_DT",
						"type": "String"
					},
					{
						"name": "FISCAL_PERIOD_LAST_UPD_DT",
						"type": "String"
					},
					{
						"name": "FISC_PERIOD_BKEY",
						"type": "String"
					},
					{
						"name": "FISC_PERIOD_CAPTION",
						"type": "String"
					},
					{
						"name": "FISC_PERIOD_CODE",
						"type": "String"
					},
					{
						"name": "FISC_PERIOD_NAME",
						"type": "String"
					},
					{
						"name": "FISC_PERIOD_SERIES",
						"type": "String"
					},
					{
						"name": "FISC_PERIOD_BEG_DT",
						"type": "String"
					},
					{
						"name": "FISC_PERIOD_END_DT",
						"type": "String"
					},
					{
						"name": "FISC_QTR_BKEY",
						"type": "String"
					},
					{
						"name": "FISC_QTR_CAPTION",
						"type": "String"
					},
					{
						"name": "FISC_QTR_CODE",
						"type": "String"
					},
					{
						"name": "FISC_QTR_NAME",
						"type": "String"
					},
					{
						"name": "FISC_QTR_SERIES",
						"type": "String"
					},
					{
						"name": "FISC_QTR_BEG_DT",
						"type": "String"
					},
					{
						"name": "FISC_QTR_END_DT",
						"type": "String"
					},
					{
						"name": "FISC_HALF_YEAR_BKEY",
						"type": "String"
					},
					{
						"name": "FISC_HALF_YEAR_CAPTION",
						"type": "String"
					},
					{
						"name": "FISC_HALF_YEAR_CODE",
						"type": "String"
					},
					{
						"name": "FISC_HALF_YEAR_NAME",
						"type": "String"
					},
					{
						"name": "FISC_HALF_YEAR_SERIES",
						"type": "String"
					},
					{
						"name": "FISC_HALF_YEAR_BEG_DT",
						"type": "String"
					},
					{
						"name": "FISC_HALF_YEAR_END_DT",
						"type": "String"
					},
					{
						"name": "FISC_YEAR_BKEY",
						"type": "String"
					},
					{
						"name": "FISC_YEAR_CAPTION",
						"type": "String"
					},
					{
						"name": "FISC_YEAR_CODE",
						"type": "String"
					},
					{
						"name": "FISC_YEAR_SERIES",
						"type": "String"
					},
					{
						"name": "FISC_YEAR_BEG_DT",
						"type": "String"
					},
					{
						"name": "FISC_YEAR_END_DT",
						"type": "String"
					},
					{
						"name": "FISC_YEAR_NAME",
						"type": "String"
					},
					{
						"name": "CAL_MONTH_BKEY",
						"type": "String"
					},
					{
						"name": "CAL_MONTH_CAPTION",
						"type": "String"
					},
					{
						"name": "CAL_MONTH_CODE",
						"type": "String"
					},
					{
						"name": "CAL_MONTH_NAME",
						"type": "String"
					},
					{
						"name": "CAL_MONTH_SERIES",
						"type": "String"
					},
					{
						"name": "CAL_MONTH_BEG_DT",
						"type": "String"
					},
					{
						"name": "CAL_MONTH_END_DT",
						"type": "String"
					},
					{
						"name": "CAL_QTR_BKEY",
						"type": "String"
					},
					{
						"name": "CAL_QTR_CAPTION",
						"type": "String"
					},
					{
						"name": "CAL_QTR_CODE",
						"type": "String"
					},
					{
						"name": "CAL_QTR_NAME",
						"type": "String"
					},
					{
						"name": "CAL_QTR_SERIES",
						"type": "String"
					},
					{
						"name": "CAL_QTR_BEG_DT",
						"type": "String"
					},
					{
						"name": "CAL_QTR_END_DT",
						"type": "String"
					},
					{
						"name": "CAL_HALF_YEAR_BKEY",
						"type": "String"
					},
					{
						"name": "CAL_HALF_YEAR_CAPTION",
						"type": "String"
					},
					{
						"name": "CAL_HALF_YEAR_CODE",
						"type": "String"
					},
					{
						"name": "CAL_HALF_YEAR_NAME",
						"type": "String"
					},
					{
						"name": "CAL_HALF_YEAR_SERIES",
						"type": "String"
					},
					{
						"name": "CAL_HALF_YEAR_BEG_DT",
						"type": "String"
					},
					{
						"name": "CAL_HALF_YEAR_END_DT",
						"type": "String"
					},
					{
						"name": "CAL_YEAR_BKEY",
						"type": "String"
					},
					{
						"name": "CAL_YEAR_CAPTION",
						"type": "String"
					},
					{
						"name": "CAL_YEAR_CODE",
						"type": "String"
					},
					{
						"name": "CAL_YEAR_SERIES",
						"type": "String"
					},
					{
						"name": "CAL_YEAR_BEG_DT",
						"type": "String"
					},
					{
						"name": "CAL_YEAR_END_DT",
						"type": "String"
					},
					{
						"name": "CAL_YEAR_NAME",
						"type": "String"
					},
					{
						"name": "SOURCE_SYSTEM",
						"type": "String"
					}
				],
				"typeProperties": {
					"format": {
						"type": "TextFormat",
						"columnDelimiter": ",",
						"rowDelimiter": "",
						"quoteChar": "\"",
						"nullValue": "",
						"treatEmptyAsNull": true,
						"skipLineCount": 0,
						"firstRowAsHeader": true
					},
					"fileName": "[parameters('TimeDimension_Source_properties_typeProperties_fileName')]",
					"folderPath": "[parameters('TimeDimension_Source_properties_typeProperties_folderPath')]"
				}
			},
			"dependsOn": []
		},
		{
			"name": "[concat(parameters('factoryName'), '/User_Arch_Dest')]",
			"type": "Microsoft.DataFactory/factories/datasets",
			"apiVersion": "2018-06-01",
			"properties": {
				"linkedServiceName": {
					"referenceName": "AzureDataLakeStore",
					"type": "LinkedServiceReference"
				},
				"annotations": [],
				"type": "AzureDataLakeStoreFile",
				"typeProperties": {
					"format": {
						"type": "OrcFormat"
					},
					"fileName": {
						"value": "[parameters('User_Arch_Dest_properties_typeProperties_fileName')]",
						"type": "Expression"
					},
					"folderPath": "[parameters('User_Arch_Dest_properties_typeProperties_folderPath')]"
				}
			},
			"dependsOn": []
		},
		{
			"name": "[concat(parameters('factoryName'), '/User_Arch_Dest_Incr')]",
			"type": "Microsoft.DataFactory/factories/datasets",
			"apiVersion": "2018-06-01",
			"properties": {
				"linkedServiceName": {
					"referenceName": "AzureDataLakeStore",
					"type": "LinkedServiceReference"
				},
				"annotations": [],
				"type": "AzureDataLakeStoreFile",
				"typeProperties": {
					"format": {
						"type": "OrcFormat"
					},
					"fileName": {
						"value": "[parameters('User_Arch_Dest_Incr_properties_typeProperties_fileName')]",
						"type": "Expression"
					},
					"folderPath": "[parameters('User_Arch_Dest_Incr_properties_typeProperties_folderPath')]"
				}
			},
			"dependsOn": []
		},
		{
			"name": "[concat(parameters('factoryName'), '/User_Arch_Src')]",
			"type": "Microsoft.DataFactory/factories/datasets",
			"apiVersion": "2018-06-01",
			"properties": {
				"linkedServiceName": {
					"referenceName": "AzureSqlDatabase_finastra",
					"type": "LinkedServiceReference"
				},
				"annotations": [],
				"type": "AzureSqlTable",
				"schema": [
					{
						"name": "Employee_ID_SUN_e_number",
						"type": "varchar"
					},
					{
						"name": "Name",
						"type": "varchar"
					},
					{
						"name": "Firstname",
						"type": "varchar"
					},
					{
						"name": "Lastname",
						"type": "varchar"
					},
					{
						"name": "Country",
						"type": "varchar"
					},
					{
						"name": "Sub_Region",
						"type": "varchar"
					},
					{
						"name": "Regional_Manager",
						"type": "varchar"
					},
					{
						"name": "ProfileId",
						"type": "varchar"
					},
					{
						"name": "DefaultCurrencyIsoCode",
						"type": "varchar"
					},
					{
						"name": "Current_FY_ILF_Quota",
						"type": "varchar"
					},
					{
						"name": "CreatedDate",
						"type": "datetime",
						"precision": 23,
						"scale": 3
					},
					{
						"name": "LastModifiedDate",
						"type": "datetime",
						"precision": 23,
						"scale": 3
					}
				],
				"typeProperties": {
					"tableName": "[[STG].[V_Sales_SFDC_User]"
				}
			},
			"dependsOn": []
		},
		{
			"name": "[concat(parameters('factoryName'), '/User_Dest')]",
			"type": "Microsoft.DataFactory/factories/datasets",
			"apiVersion": "2018-06-01",
			"properties": {
				"linkedServiceName": {
					"referenceName": "AzureSqlDatabase_finastra",
					"type": "LinkedServiceReference"
				},
				"annotations": [],
				"type": "AzureSqlTable",
				"schema": [
					{
						"name": "Id",
						"type": "nvarchar"
					},
					{
						"name": "Employee_ID_SUN_e_number",
						"type": "nvarchar"
					},
					{
						"name": "Name",
						"type": "nvarchar"
					},
					{
						"name": "Firstname",
						"type": "nvarchar"
					},
					{
						"name": "Lastname",
						"type": "nvarchar"
					},
					{
						"name": "Country",
						"type": "nvarchar"
					},
					{
						"name": "Sub_Region",
						"type": "nvarchar"
					},
					{
						"name": "Regional_Manager",
						"type": "nvarchar"
					},
					{
						"name": "ProfileId",
						"type": "nvarchar"
					},
					{
						"name": "DefaultCurrencyIsoCode",
						"type": "nvarchar"
					},
					{
						"name": "Current_FY_ILF_Quota",
						"type": "nvarchar"
					},
					{
						"name": "CreatedDate",
						"type": "nvarchar"
					},
					{
						"name": "LastModifiedDate",
						"type": "nvarchar"
					},
					{
						"name": "Rec_CRE_TMS",
						"type": "datetime",
						"precision": 23,
						"scale": 3
					}
				],
				"typeProperties": {
					"tableName": "[[STG].[Sales_SFDC_User]"
				}
			},
			"dependsOn": []
		},
		{
			"name": "[concat(parameters('factoryName'), '/User_Dest_Inc')]",
			"type": "Microsoft.DataFactory/factories/datasets",
			"apiVersion": "2018-06-01",
			"properties": {
				"linkedServiceName": {
					"referenceName": "AzureSqlDatabase_finastra",
					"type": "LinkedServiceReference"
				},
				"annotations": [],
				"type": "AzureSqlTable",
				"schema": [
					{
						"name": "Employee_ID_SUN_e_number",
						"type": "nvarchar"
					},
					{
						"name": "Name",
						"type": "nvarchar"
					},
					{
						"name": "Firstname",
						"type": "nvarchar"
					},
					{
						"name": "Lastname",
						"type": "nvarchar"
					},
					{
						"name": "Country",
						"type": "nvarchar"
					},
					{
						"name": "Sub_Region",
						"type": "nvarchar"
					},
					{
						"name": "Regional_Manager",
						"type": "nvarchar"
					},
					{
						"name": "ProfileId",
						"type": "nvarchar"
					},
					{
						"name": "DefaultCurrencyIsoCode",
						"type": "nvarchar"
					},
					{
						"name": "Current_FY_ILF_Quota",
						"type": "nvarchar"
					},
					{
						"name": "CreatedDate",
						"type": "nvarchar"
					},
					{
						"name": "LastModifiedDate",
						"type": "nvarchar"
					},
					{
						"name": "Rec_CRE_TMS",
						"type": "datetime",
						"precision": 23,
						"scale": 3
					}
				],
				"typeProperties": {
					"tableName": "[[STG].[Sales_SFDC_User]"
				}
			},
			"dependsOn": []
		},
		{
			"name": "[concat(parameters('factoryName'), '/User_LastCreate')]",
			"type": "Microsoft.DataFactory/factories/datasets",
			"apiVersion": "2018-06-01",
			"properties": {
				"linkedServiceName": {
					"referenceName": "AzureSqlDatabase_finastra",
					"type": "LinkedServiceReference"
				},
				"annotations": [],
				"type": "AzureSqlTable",
				"schema": [],
				"typeProperties": {}
			},
			"dependsOn": []
		},
		{
			"name": "[concat(parameters('factoryName'), '/User_Source')]",
			"type": "Microsoft.DataFactory/factories/datasets",
			"apiVersion": "2018-06-01",
			"properties": {
				"linkedServiceName": {
					"referenceName": "Salesforce1",
					"type": "LinkedServiceReference"
				},
				"annotations": [],
				"type": "SalesforceObject",
				"structure": [
					{
						"name": "Id",
						"type": "String"
					},
					{
						"name": "Employee_ID_SUN_e_number__c",
						"type": "String"
					},
					{
						"name": "Name",
						"type": "String"
					},
					{
						"name": "FirstName",
						"type": "String"
					},
					{
						"name": "LastName",
						"type": "String"
					},
					{
						"name": "Country",
						"type": "String"
					},
					{
						"name": "Sub_Region__c",
						"type": "String"
					},
					{
						"name": "Regional_Manager__c",
						"type": "String"
					},
					{
						"name": "ProfileId",
						"type": "String"
					},
					{
						"name": "DefaultCurrencyIsoCode",
						"type": "String"
					},
					{
						"name": "Current_FY_ILF_Quota__c",
						"type": "Decimal"
					},
					{
						"name": "CreatedDate",
						"type": "DateTime"
					},
					{
						"name": "LastModifiedDate",
						"type": "DateTime"
					}
				],
				"typeProperties": {
					"objectApiName": "User"
				}
			},
			"dependsOn": []
		},
		{
			"name": "[concat(parameters('factoryName'), '/User_Source_Inc')]",
			"type": "Microsoft.DataFactory/factories/datasets",
			"apiVersion": "2018-06-01",
			"properties": {
				"linkedServiceName": {
					"referenceName": "Salesforce1",
					"type": "LinkedServiceReference"
				},
				"annotations": [],
				"type": "SalesforceObject",
				"typeProperties": {
					"objectApiName": "User"
				}
			},
			"dependsOn": []
		},
		{
			"name": "[concat(parameters('factoryName'), '/User_arch_Source')]",
			"type": "Microsoft.DataFactory/factories/datasets",
			"apiVersion": "2018-06-01",
			"properties": {
				"linkedServiceName": {
					"referenceName": "AzureSqlDatabase_finastra",
					"type": "LinkedServiceReference"
				},
				"annotations": [],
				"type": "AzureSqlTable",
				"schema": [
					{
						"name": "Employee_ID_SUN_e_number",
						"type": "varchar"
					},
					{
						"name": "Name",
						"type": "varchar"
					},
					{
						"name": "Firstname",
						"type": "varchar"
					},
					{
						"name": "Lastname",
						"type": "varchar"
					},
					{
						"name": "Country",
						"type": "varchar"
					},
					{
						"name": "Sub_Region",
						"type": "varchar"
					},
					{
						"name": "Regional_Manager",
						"type": "varchar"
					},
					{
						"name": "ProfileId",
						"type": "varchar"
					},
					{
						"name": "DefaultCurrencyIsoCode",
						"type": "varchar"
					},
					{
						"name": "Current_FY_ILF_Quota",
						"type": "varchar"
					},
					{
						"name": "CreatedDate",
						"type": "datetime",
						"precision": 23,
						"scale": 3
					},
					{
						"name": "LastModifiedDate",
						"type": "datetime",
						"precision": 23,
						"scale": 3
					}
				],
				"typeProperties": {
					"tableName": "[[STG].[V_Sales_SFDC_User]"
				}
			},
			"dependsOn": []
		},
		{
			"name": "[concat(parameters('factoryName'), '/User_lastMod')]",
			"type": "Microsoft.DataFactory/factories/datasets",
			"apiVersion": "2018-06-01",
			"properties": {
				"linkedServiceName": {
					"referenceName": "AzureSqlDatabase_finastra",
					"type": "LinkedServiceReference"
				},
				"annotations": [],
				"type": "AzureSqlTable",
				"schema": [],
				"typeProperties": {}
			},
			"dependsOn": []
		},
		{
			"name": "[concat(parameters('factoryName'), '/V_HR_Maclean_EXM_Location_Archive_Destination')]",
			"type": "Microsoft.DataFactory/factories/datasets",
			"apiVersion": "2018-06-01",
			"properties": {
				"linkedServiceName": {
					"referenceName": "AzureDataLakeStore",
					"type": "LinkedServiceReference"
				},
				"annotations": [],
				"type": "AzureDataLakeStoreFile",
				"typeProperties": {
					"format": {
						"type": "TextFormat",
						"columnDelimiter": ",",
						"rowDelimiter": "",
						"quoteChar": "\"",
						"nullValue": "",
						"treatEmptyAsNull": true,
						"skipLineCount": 0,
						"firstRowAsHeader": true
					},
					"compression": {
						"type": "GZip",
						"level": "Optimal"
					},
					"fileName": {
						"value": "[parameters('V_HR_Maclean_EXM_Location_Archive_Destination_properties_typeProperties_fileName')]",
						"type": "Expression"
					},
					"folderPath": "[parameters('V_HR_Maclean_EXM_Location_Archive_Destination_properties_typeProperties_folderPath')]"
				}
			},
			"dependsOn": []
		},
		{
			"name": "[concat(parameters('factoryName'), '/V_HR_Maclean_EXM_Location_Directory_Archive_Destination')]",
			"type": "Microsoft.DataFactory/factories/datasets",
			"apiVersion": "2018-06-01",
			"properties": {
				"linkedServiceName": {
					"referenceName": "AzureDataLakeStore",
					"type": "LinkedServiceReference"
				},
				"annotations": [],
				"type": "AzureDataLakeStoreFile",
				"typeProperties": {
					"format": {
						"type": "TextFormat",
						"columnDelimiter": ",",
						"rowDelimiter": "",
						"quoteChar": "\"",
						"nullValue": "",
						"treatEmptyAsNull": true,
						"skipLineCount": 0,
						"firstRowAsHeader": true
					},
					"compression": {
						"type": "GZip",
						"level": "Optimal"
					},
					"fileName": {
						"value": "[parameters('V_HR_Maclean_EXM_Location_Directory_Archive_Destination_properties_typeProperties_fileName')]",
						"type": "Expression"
					},
					"folderPath": "[parameters('V_HR_Maclean_EXM_Location_Directory_Archive_Destination_properties_typeProperties_folderPath')]"
				}
			},
			"dependsOn": []
		},
		{
			"name": "[concat(parameters('factoryName'), '/test')]",
			"type": "Microsoft.DataFactory/factories/datasets",
			"apiVersion": "2018-06-01",
			"properties": {
				"linkedServiceName": {
					"referenceName": "FileShare",
					"type": "LinkedServiceReference"
				},
				"annotations": [],
				"type": "FileShare",
				"typeProperties": {
					"format": {
						"type": "TextFormat",
						"columnDelimiter": ",",
						"rowDelimiter": "",
						"nullValue": "\\N",
						"treatEmptyAsNull": true,
						"skipLineCount": 0,
						"firstRowAsHeader": false
					},
					"fileName": "[parameters('test_properties_typeProperties_fileName')]",
					"folderPath": "[parameters('test_properties_typeProperties_folderPath')]"
				}
			},
			"dependsOn": []
		},
		{
			"name": "[concat(parameters('factoryName'), '/test1')]",
			"type": "Microsoft.DataFactory/factories/datasets",
			"apiVersion": "2018-06-01",
			"properties": {
				"linkedServiceName": {
					"referenceName": "FileShare",
					"type": "LinkedServiceReference"
				},
				"annotations": [],
				"type": "DelimitedText",
				"typeProperties": {
					"location": {
						"type": "FileServerLocation",
						"fileName": "FinanceActuals_20190430.csv",
						"folderPath": "CEOCFO/Finance"
					},
					"columnDelimiter": ",",
					"escapeChar": "\\",
					"firstRowAsHeader": true,
					"quoteChar": "\""
				},
				"schema": [
					{
						"name": "GL Period",
						"type": "String"
					},
					{
						"name": "TransID",
						"type": "String"
					},
					{
						"name": "Region",
						"type": "String"
					},
					{
						"name": "Softrax",
						"type": "String"
					},
					{
						"name": "Name",
						"type": "String"
					},
					{
						"name": "Sales Rep",
						"type": "String"
					},
					{
						"name": "LOB",
						"type": "String"
					},
					{
						"name": "Product",
						"type": "String"
					},
					{
						"name": "Sum of Booking ACV",
						"type": "String"
					},
					{
						"name": "Sum of Renewal ACV",
						"type": "String"
					}
				]
			},
			"dependsOn": []
		},
		{
			"name": "[concat(parameters('factoryName'), '/test11')]",
			"type": "Microsoft.DataFactory/factories/datasets",
			"apiVersion": "2018-06-01",
			"properties": {
				"linkedServiceName": {
					"referenceName": "AzureDataLakeStore",
					"type": "LinkedServiceReference"
				},
				"annotations": [],
				"type": "DelimitedText",
				"typeProperties": {
					"location": {
						"type": "AzureDataLakeStoreLocation",
						"fileName": "Financial_Actuals",
						"folderPath": "LandingArchive/CEOCFO/Sales/CM_OrderBook"
					},
					"columnDelimiter": ",",
					"compressionCodec": "gzip",
					"compressionLevel": "Optimal",
					"escapeChar": "\\",
					"firstRowAsHeader": true,
					"quoteChar": "\""
				},
				"schema": []
			},
			"dependsOn": []
		},
		{
			"name": "[concat(parameters('factoryName'), '/Delete old Landing Files')]",
			"type": "Microsoft.DataFactory/factories/pipelines",
			"apiVersion": "2018-06-01",
			"properties": {
				"description": "Delete files more than 30 days",
				"activities": [
					{
						"name": "Delete HR",
						"type": "Delete",
						"dependsOn": [
							{
								"activity": "Delete Forecast Plan",
								"dependencyConditions": [
									"Completed"
								]
							}
						],
						"policy": {
							"timeout": "7.00:00:00",
							"retry": 0,
							"retryIntervalInSeconds": 30,
							"secureOutput": false,
							"secureInput": false
						},
						"userProperties": [],
						"typeProperties": {
							"dataset": {
								"referenceName": "FileShareDelete",
								"type": "DatasetReference",
								"parameters": {}
							},
							"enableLogging": false
						}
					},
					{
						"name": "Delete Customer Support",
						"type": "Delete",
						"dependsOn": [],
						"policy": {
							"timeout": "7.00:00:00",
							"retry": 0,
							"retryIntervalInSeconds": 30,
							"secureOutput": false,
							"secureInput": false
						},
						"userProperties": [],
						"typeProperties": {
							"dataset": {
								"referenceName": "FileShareDelete2",
								"type": "DatasetReference",
								"parameters": {}
							},
							"enableLogging": false
						}
					},
					{
						"name": "Delete Finance",
						"type": "Delete",
						"dependsOn": [
							{
								"activity": "Delete HR",
								"dependencyConditions": [
									"Completed"
								]
							}
						],
						"policy": {
							"timeout": "7.00:00:00",
							"retry": 0,
							"retryIntervalInSeconds": 30,
							"secureOutput": false,
							"secureInput": false
						},
						"userProperties": [],
						"typeProperties": {
							"dataset": {
								"referenceName": "FileShareDelete3",
								"type": "DatasetReference",
								"parameters": {}
							},
							"enableLogging": false
						}
					},
					{
						"name": "Delete Marketing",
						"type": "Delete",
						"dependsOn": [
							{
								"activity": "Delete Finance",
								"dependencyConditions": [
									"Completed"
								]
							}
						],
						"policy": {
							"timeout": "7.00:00:00",
							"retry": 0,
							"retryIntervalInSeconds": 30,
							"secureOutput": false,
							"secureInput": false
						},
						"userProperties": [],
						"typeProperties": {
							"dataset": {
								"referenceName": "FileShareDelete4",
								"type": "DatasetReference",
								"parameters": {}
							},
							"enableLogging": false
						}
					},
					{
						"name": "Delete Sales",
						"type": "Delete",
						"dependsOn": [
							{
								"activity": "Delete Marketing",
								"dependencyConditions": [
									"Completed"
								]
							}
						],
						"policy": {
							"timeout": "7.00:00:00",
							"retry": 0,
							"retryIntervalInSeconds": 30,
							"secureOutput": false,
							"secureInput": false
						},
						"userProperties": [],
						"typeProperties": {
							"dataset": {
								"referenceName": "FileShareDelete5",
								"type": "DatasetReference",
								"parameters": {}
							},
							"enableLogging": false
						}
					},
					{
						"name": "Delete Forecast Plan",
						"type": "Delete",
						"dependsOn": [
							{
								"activity": "Delete Customer Support",
								"dependencyConditions": [
									"Completed"
								]
							}
						],
						"policy": {
							"timeout": "7.00:00:00",
							"retry": 0,
							"retryIntervalInSeconds": 30,
							"secureOutput": false,
							"secureInput": false
						},
						"userProperties": [],
						"typeProperties": {
							"dataset": {
								"referenceName": "FileShareDelete6",
								"type": "DatasetReference",
								"parameters": {}
							},
							"enableLogging": false
						}
					}
				],
				"folder": {
					"name": "ETL Jobs"
				},
				"annotations": []
			},
			"dependsOn": []
		},
		{
			"name": "[concat(parameters('factoryName'), '/DimDate')]",
			"type": "Microsoft.DataFactory/factories/pipelines",
			"apiVersion": "2018-06-01",
			"properties": {
				"activities": [
					{
						"name": "STG",
						"type": "Copy",
						"dependsOn": [],
						"policy": {
							"timeout": "7.00:00:00",
							"retry": 0,
							"retryIntervalInSeconds": 30,
							"secureOutput": false,
							"secureInput": false
						},
						"userProperties": [],
						"typeProperties": {
							"source": {
								"type": "FileSystemSource",
								"recursive": true
							},
							"sink": {
								"type": "SqlSink",
								"writeBatchSize": 10000
							},
							"enableStaging": false,
							"translator": {
								"type": "TabularTranslator",
								"columnMappings": {
									"DATE_SKEY": "DATE_SKEY",
									"DATE_CREAT_DT": "DATE_CREAT_DT",
									"DATE_LAST_UPD_DT": "DATE_LAST_UPD_DT",
									"DATE_BKEY": "DATE_BKEY",
									"DATE_CAPTION": "DATE_CAPTION",
									"DATE_CODE": "DATE_CODE",
									"DATE_DT": "DATE_DT",
									"DATE_DAY_NAME": "DATE_DAY_NAME",
									"DATE_SERIES": "DATE_SERIES",
									"DATE_DAY_OF_WEEK": "DATE_DAY_OF_WEEK",
									"CAL_MONTH_BKEY": "CAL_MONTH_BKEY",
									"CAL_MONTH_CAPTION": "CAL_MONTH_CAPTION",
									"CAL_MONTH_CODE": "CAL_MONTH_CODE",
									"CAL_MONTH_NAME": "CAL_MONTH_NAME",
									"CAL_MONTH_SERIES": "CAL_MONTH_SERIES",
									"CAL_MONTH_BEG_DT": "CAL_MONTH_BEG_DT",
									"CAL_MONTH_END_DT": "CAL_MONTH_END_DT",
									"CAL_QTR_BKEY": "CAL_QTR_BKEY",
									"CAL_QTR_CAPTION": "CAL_QTR_CAPTION",
									"CAL_QTR_CODE": "CAL_QTR_CODE",
									"CAL_QTR_NAME": "CAL_QTR_NAME",
									"CAL_QTR_SERIES": "CAL_QTR_SERIES",
									"CAL_QTR_BEG_DT": "CAL_QTR_BEG_DT",
									"CAL_QTR_END_DT": "CAL_QTR_END_DT",
									"CAL_HALF_YEAR_BKEY": "CAL_HALF_YEAR_BKEY",
									"CAL_HALF_YEAR_CAPTION": "CAL_HALF_YEAR_CAPTION",
									"CAL_HALF_YEAR_CODE": "CAL_HALF_YEAR_CODE",
									"CAL_HALF_YEAR_NAME": "CAL_HALF_YEAR_NAME",
									"CAL_HALF_YEAR_SERIES": "CAL_HALF_YEAR_SERIES",
									"CAL_HALF_YEAR_BEG_DT": "CAL_HALF_YEAR_BEG_DT",
									"CAL_HALF_YEAR_END_DT": "CAL_HALF_YEAR_END_DT",
									"CAL_YEAR_BKEY": "CAL_YEAR_BKEY",
									"CAL_YEAR_CAPTION": "CAL_YEAR_CAPTION",
									"CAL_YEAR_CODE": "CAL_YEAR_CODE",
									"CAL_YEAR_SERIES": "CAL_YEAR_SERIES",
									"CAL_YEAR_BEG_DT": "CAL_YEAR_BEG_DT",
									"CAL_YEAR_END_DT": "CAL_YEAR_END_DT",
									"FISC_PERIOD_BKEY": "FISC_PERIOD_BKEY",
									"FISC_PERIOD_CAPTION": "FISC_PERIOD_CAPTION",
									"FISC_PERIOD_CODE": "FISC_PERIOD_CODE",
									"FISC_PERIOD_NAME": "FISC_PERIOD_NAME",
									"FISC_PERIOD_SERIES": "FISC_PERIOD_SERIES",
									"FISC_PERIOD_BEG_DT": "FISC_PERIOD_BEG_DT",
									"FISC_PERIOD_END_DT": "FISC_PERIOD_END_DT",
									"FISC_QTR_BKEY": "FISC_QTR_BKEY",
									"FISC_QTR_CAPTION": "FISC_QTR_CAPTION",
									"FISC_QTR_CODE": "FISC_QTR_CODE",
									"FISC_QTR_NAME": "FISC_QTR_NAME",
									"FISC_QTR_SERIES": "FISC_QTR_SERIES",
									"FISC_QTR_BEG_DT": "FISC_QTR_BEG_DT",
									"FISC_QTR_END_DT": "FISC_QTR_END_DT",
									"FISC_HALF_YEAR_BKEY": "FISC_HALF_YEAR_BKEY",
									"FISC_HALF_YEAR_CAPTION": "FISC_HALF_YEAR_CAPTION",
									"FISC_HALF_YEAR_CODE": "FISC_HALF_YEAR_CODE",
									"FISC_HALF_YEAR_NAME": "FISC_HALF_YEAR_NAME",
									"FISC_HALF_YEAR_SERIES": "FISC_HALF_YEAR_SERIES",
									"FISC_HALF_YEAR_BEG_DT": "FISC_HALF_YEAR_BEG_DT",
									"FISC_HALF_YEAR_END_DT": "FISC_HALF_YEAR_END_DT",
									"FISC_YEAR_BKEY": "FISC_YEAR_BKEY",
									"FISC_YEAR_CAPTION": "FISC_YEAR_CAPTION",
									"FISC_YEAR_CODE": "FISC_YEAR_CODE",
									"FISC_YEAR_SERIES": "FISC_YEAR_SERIES",
									"FISC_YEAR_BEG_DT": "FISC_YEAR_BEG_DT",
									"FISC_YEAR_END_DT": "FISC_YEAR_END_DT",
									"FISC_YEAR_NAME": "FISC_YEAR_NAME",
									"FISC_WEEK_BKEY": "FISC_WEEK_BKEY",
									"FISC_WEEK_CAPTION": "FISC_WEEK_CAPTION",
									"FISC_WEEK_CODE": "FISC_WEEK_CODE",
									"FISC_WEEK_NAME": "FISC_WEEK_NAME",
									"FISC_WEEK_SERIES": "FISC_WEEK_SERIES",
									"FISC_WEEK_BEG_DT": "FISC_WEEK_BEG_DT",
									"FISC_WEEK_END_DT": "FISC_WEEK_END_DT",
									"SOURCE_SYSTEM": "SOURCE_SYSTEM"
								}
							}
						},
						"inputs": [
							{
								"referenceName": "TimeDimensionDate_Source",
								"type": "DatasetReference",
								"parameters": {}
							}
						],
						"outputs": [
							{
								"referenceName": "TimeDimensionDate_Destination",
								"type": "DatasetReference",
								"parameters": {}
							}
						]
					},
					{
						"name": "Loading dbo table",
						"type": "SqlServerStoredProcedure",
						"dependsOn": [
							{
								"activity": "STG",
								"dependencyConditions": [
									"Succeeded"
								]
							}
						],
						"policy": {
							"timeout": "7.00:00:00",
							"retry": 0,
							"retryIntervalInSeconds": 30,
							"secureOutput": false,
							"secureInput": false
						},
						"userProperties": [],
						"typeProperties": {
							"storedProcedureName": "[[dbo].[sp_INT_ApplyDimDate]"
						},
						"linkedServiceName": {
							"referenceName": "AzureSqlDatabase_finastra",
							"type": "LinkedServiceReference"
						}
					},
					{
						"name": "Archiving data in DL",
						"type": "Copy",
						"dependsOn": [
							{
								"activity": "Loading dbo table",
								"dependencyConditions": [
									"Succeeded"
								]
							}
						],
						"policy": {
							"timeout": "7.00:00:00",
							"retry": 0,
							"retryIntervalInSeconds": 30,
							"secureOutput": false,
							"secureInput": false
						},
						"userProperties": [],
						"typeProperties": {
							"source": {
								"type": "FileSystemSource",
								"recursive": true
							},
							"sink": {
								"type": "AzureDataLakeStoreSink"
							},
							"enableStaging": false
						},
						"inputs": [
							{
								"referenceName": "TimeDimensionDate_Source",
								"type": "DatasetReference",
								"parameters": {}
							}
						],
						"outputs": [
							{
								"referenceName": "TimeDimensionDate_Archive_Destination",
								"type": "DatasetReference",
								"parameters": {}
							}
						]
					}
				],
				"folder": {
					"name": "Time"
				},
				"annotations": []
			},
			"dependsOn": []
		}
	]
}